plone.recipe.zope2instance-8.0.1-py3.11-nspkg.pth
plone/recipe/zope2instance/__init__.py
plone/recipe/zope2instance/ctl.py
plone/recipe/zope2instance/make.py
plone/recipe/zope2instance/recipe.py
plone/recipe/zope2instance/sentry.py
plone/recipe/zope2instance/wsgischema.xml
plone/recipe/zope2instance/skel4/bin/README.txt
plone/recipe/zope2instance/skel4/etc/site.zcml
plone/recipe/zope2instance/skel4/var/README.txt
plone/recipe/zope2instance/tests/__init__.py
plone/recipe/zope2instance/tests/test_docs.py
plone/recipe/zope2instance/tests/test_wsgi_template.py
plone/recipe/zope2instance/tests/test_wsgischema.py
plone/recipe/zope2instance/tests/wsgi.rst
plone/recipe/zope2instance/tests/zope2instance_base.rst
plone/recipe/zope2instance/tests/zope2instance_beforestorage.rst
plone/recipe/zope2instance/tests/zope2instance_blobstorage.rst
plone/recipe/zope2instance/tests/zope2instance_demostorage.rst
plone/recipe/zope2instance/tests/zope2instance_relstorage.rst
plone/recipe/zope2instance/tests/zope2instance_tempstorage_off.rst
plone/recipe/zope2instance/tests/zope2instance_zeostorage.rst
plone/recipe/zope2instance/tests/zope2instance_zlibstorage.rst
plone_recipe_zope2instance-8.0.1.dist-info/METADATA
plone_recipe_zope2instance-8.0.1.dist-info/WHEEL
plone_recipe_zope2instance-8.0.1.dist-info/entry_points.txt
plone_recipe_zope2instance-8.0.1.dist-info/namespace_packages.txt
plone_recipe_zope2instance-8.0.1.dist-info/top_level.txt
plone_recipe_zope2instance-8.0.1.dist-info/RECORD
