Metadata-Version: 2.4
Name: plone.recipe.zope2instance
Version: 8.0.1
Summary: Buildout recipe for creating a Zope instance
Home-page: https://github.com/plone/plone.recipe.zope2instance
Author: Hanno Schlichting
Author-email: hanno@hannosch.eu
Maintainer: Plone Release Team
Maintainer-email: releaseteam@plone.org
License: ZPL 2.1
Keywords: zope buildout
Classifier: Development Status :: 6 - Mature
Classifier: Framework :: Buildout
Classifier: Framework :: Plone
Classifier: Framework :: Plone :: 6.0
Classifier: Framework :: Plone :: 6.1
Classifier: Framework :: Plone :: 6.2
Classifier: Framework :: Plone :: Core
Classifier: Framework :: Zope :: 5
Classifier: License :: OSI Approved :: Zope Public License
Classifier: Programming Language :: Python
Classifier: Programming Language :: Python :: 3.9
Classifier: Programming Language :: Python :: 3.10
Classifier: Programming Language :: Python :: 3.11
Classifier: Programming Language :: Python :: 3.12
Classifier: Programming Language :: Python :: 3.13
Classifier: Programming Language :: Python :: Implementation :: CPython
Requires-Python: >=3.9
Requires-Dist: zc.buildout
Requires-Dist: setuptools
Requires-Dist: zc.recipe.egg
Requires-Dist: Zope>=5.0
Requires-Dist: ZODB>=5.1.1
Requires-Dist: ZEO
Requires-Dist: waitress>=1.2.0
Requires-Dist: Paste
Requires-Dist: python-dotenv
Provides-Extra: test
Requires-Dist: zope.testrunner; extra == "test"
Requires-Dist: sentry-sdk; extra == "test"
Provides-Extra: sentry
Requires-Dist: sentry-sdk; extra == "sentry"
Provides-Extra: profile
Requires-Dist: repoze.profile; extra == "profile"
Dynamic: author
Dynamic: author-email
Dynamic: classifier
Dynamic: description
Dynamic: home-page
Dynamic: keywords
Dynamic: license
Dynamic: maintainer
Dynamic: maintainer-email
Dynamic: provides-extra
Dynamic: requires-dist
Dynamic: requires-python
Dynamic: summary
